shirokumas/__init__.py
shirokumas/_agg.py
shirokumas/_base.py
shirokumas/_binarize.py
shirokumas/_count.py
shirokumas/_exceptions.py
shirokumas/_null.py
shirokumas/_oof.py
shirokumas/_ordinal.py
shirokumas/_target.py
shirokumas-0.0.4.dist-info/LICENSE
shirokumas-0.0.4.dist-info/METADATA
shirokumas-0.0.4.dist-info/WHEEL
shirokumas-0.0.4.dist-info/top_level.txt
shirokumas-0.0.4.dist-info/RECORD
